listrology/__init__.py
listrology-1.0.1.dist-info/METADATA
listrology-1.0.1.dist-info/WHEEL
listrology-1.0.1.dist-info/top_level.txt
listrology-1.0.1.dist-info/RECORD
