Metadata-Version: 2.1
Name: listrology
Version: 1.0.1
Summary: extended list methods
Project-URL: Homepage, https://github.com/tovicheung/listrology
Classifier: License :: OSI Approved :: MIT License
Classifier: Programming Language :: Python
Classifier: Programming Language :: Python :: 3
